type_hint_checker/__init__.py
type_hint_checker/checkers.py
type_hint_checker/exceptions.py
type_hint_checker/file_parser.py
type_hint_checker/main.py
type_hint_checker-0.1.13.dist-info/LICENSE
type_hint_checker-0.1.13.dist-info/METADATA
type_hint_checker-0.1.13.dist-info/WHEEL
type_hint_checker-0.1.13.dist-info/entry_points.txt
type_hint_checker-0.1.13.dist-info/top_level.txt
type_hint_checker-0.1.13.dist-info/RECORD
