Metadata-Version: 2.1
Name: type_hint_checker
Version: 0.1.13
Summary: Check that all python files have type hints
Home-page: https://github.com/PaulinaPacyna
Author: Paulina Pacyna
License: MIT
License-File: LICENSE
